aaaai/RAG.py
aaaai/VDB.py
aaaai/__init__.py
aaaai/agent.py
aaaai/orchestra.py
aaaai/white.py
aaaai-0.3.0.dist-info/licenses/LICENSE
aaaai-0.3.0.dist-info/METADATA
aaaai-0.3.0.dist-info/WHEEL
aaaai-0.3.0.dist-info/top_level.txt
aaaai-0.3.0.dist-info/RECORD
