Metadata-Version: 2.4
Name: aaaai
Version: 0.3.0
Summary: All Agent And AI
Home-page: https://github.com/algonouir/aaaai
Author: Mahdi Nouri
Author-email: Mahdi Nouri <algo.mahdi.nouri@gmail.com>
License-Expression: MIT
Classifier: Programming Language :: Python :: 3
Classifier: Operating System :: OS Independent
Requires-Python: >=3.10
License-File: LICENSE
Requires-Dist: annotated-types==0.7.0
Requires-Dist: anyio==4.9.0
Requires-Dist: certifi==2025.7.14
Requires-Dist: charset-normalizer==3.4.2
Requires-Dist: greenlet==3.2.3
Requires-Dist: h11==0.16.0
Requires-Dist: httpcore==1.0.9
Requires-Dist: httpx==0.28.1
Requires-Dist: idna==3.10
Requires-Dist: jsonpatch==1.33
Requires-Dist: jsonpointer==3.0.0
Requires-Dist: langchain==0.3.26
Requires-Dist: langchain-core==0.3.69
Requires-Dist: langchain-ollama==0.3.4
Requires-Dist: langchain-text-splitters==0.3.8
Requires-Dist: langsmith==0.4.6
Requires-Dist: ollama==0.5.1
Requires-Dist: orjson==3.11.0
Requires-Dist: packaging==25.0
Requires-Dist: pydantic==2.11.7
Requires-Dist: pydantic_core==2.33.2
Requires-Dist: PyYAML==6.0.2
Requires-Dist: requests==2.32.4
Requires-Dist: requests-toolbelt==1.0.0
Requires-Dist: sniffio==1.3.1
Requires-Dist: SQLAlchemy==2.0.41
Requires-Dist: tenacity==9.1.2
Requires-Dist: typing-inspection==0.4.1
Requires-Dist: typing_extensions==4.14.1
Requires-Dist: urllib3==2.5.0
Requires-Dist: zstandard==0.23.0
Dynamic: author
Dynamic: home-page
Dynamic: license-file
